azure/mgmt/customproviders/__init__.py
azure/mgmt/customproviders/_configuration.py
azure/mgmt/customproviders/_customproviders.py
azure/mgmt/customproviders/_version.py
azure/mgmt/customproviders/aio/__init__.py
azure/mgmt/customproviders/aio/_configuration.py
azure/mgmt/customproviders/aio/_customproviders.py
azure/mgmt/customproviders/aio/operations/__init__.py
azure/mgmt/customproviders/aio/operations/_associations_operations.py
azure/mgmt/customproviders/aio/operations/_custom_resource_provider_operations.py
azure/mgmt/customproviders/aio/operations/_operations.py
azure/mgmt/customproviders/models/__init__.py
azure/mgmt/customproviders/models/_customproviders_enums.py
azure/mgmt/customproviders/models/_models.py
azure/mgmt/customproviders/models/_models_py3.py
azure/mgmt/customproviders/operations/__init__.py
azure/mgmt/customproviders/operations/_associations_operations.py
azure/mgmt/customproviders/operations/_custom_resource_provider_operations.py
azure/mgmt/customproviders/operations/_operations.py
azure_mgmt_customproviders-1.0.0.dist-info/METADATA
azure_mgmt_customproviders-1.0.0.dist-info/WHEEL
azure_mgmt_customproviders-1.0.0.dist-info/top_level.txt
azure_mgmt_customproviders-1.0.0.dist-info/RECORD
